[
  {
    "id": 1,
    "question": "Do you own a mattress?",
    "options": [
      "Yes",
      "No"
    ],
    "correctAnswer": ""
  },
  {
    "id": 2,
    "question": "How old is your mattress?",
    "options": [
      "Within 1 year",
      "1-3 years",
      "3-5 years",
      "More than 5 years"
    ],
    "correctAnswer": ""
  },
  {
    "id": 3,
    "question": "What is your main channel for buying mattresses?",
    "options": [
      "Furniture mall",
      "Online mall",
      "Brand stores",
      "Supermarket",
      "Other"
    ],
    "correctAnswer": ""
  },
  {
    "id": 4,
    "question": "What was your budget when you bought the mattress?",
    "options": [
      "Less than 500 $",
      "501-1000 $",
      "1001-2000 $",
      "2001-5000 $",
      "More than 5000 $"
    ],
    "correctAnswer": ""
  },
  {
    "id": 5,
    "question": "When you choose a mattress, what is the most concerned factor?",
    "options": [
      "Comfort",
      "Price",
      "Brand",
      "Material",
      "Dimensions"
    ],
    "correctAnswer": ""
  },
  {
    "id": 6,
    "question": "What is your mattress size?",
    "options": [
      "Single bed (0.9-1.2 m)",
      "Standard double bed (1.5m)",
      "Extra double bed (1.8m)",
      "Other"
    ],
    "correctAnswer": ""
  },
  {
    "id": 7,
    "question": "What is the material of your mattress?",
    "options": [
      "Spring",
      "Latex",
      "Memory pad",
      "Brown mat",
      "Other"
    ],
    "correctAnswer": ""
  },
  {
    "id": 8,
    "question": "How soft and hard is your mattress?",
    "options": [
      "Soft",
      "Moderate",
      "Hard"
    ],
    "correctAnswer": ""
  },
  {
    "id": 9,
    "question": "How much time do you spend sleeping on the mattress every day?",
    "options": [
      "Less than 6 hours",
      "6-8 hours",
      "8-10 hours",
      "More than 10 hours"
    ],
    "correctAnswer": ""
  },
  {
    "id": 10,
    "question": "Have you ever had an uncomfortable mattress that interfered with your sleep?",
    "options": [
      "Often",
      "Occasionally",
      "Rarely",
      "Never"
    ],
    "correctAnswer": ""
  },
  {
    "id": 11,
    "question": "Do you think the mattress has a great impact on the quality of sleep?",
    "options": [
      "Very big",
      "It's relatively large",
      "General",
      "Relatively small",
      "Very small"
    ],
    "correctAnswer": ""
  },
  {
    "id": 12,
    "question": "Do you clean your mattress regularly?",
    "options": [
      "Every week",
      "Monthly",
      "Every quarter",
      "Rarely cleans",
      "Never cleans"
    ],
    "correctAnswer": ""
  },
  {
    "id": 13,
    "question": "How do you clean your mattress?",
    "options": [
      "Vacuum",
      "Wipe",
      "Turn over",
      "Have it professionally cleaned",
      "Other"
    ],
    "correctAnswer": ""
  },
  {
    "id": 14,
    "question": "Do you know the characteristics of different mattresses?",
    "options": [
      "Very well",
      "Know something about it",
      "Not really",
      "Not at all"
    ],
    "correctAnswer": ""
  },
  {
    "id": 15,
    "question": "Are you willing to change your mattress to improve your sleep quality?",
    "options": [
      "I'd love to",
      "More willing",
      "Not sure",
      "Not really",
      "Very reluctant"
    ],
    "correctAnswer": ""
  },
  {
    "id": 16,
    "question": "When you buy a mattress, do you refer to the reviews of other consumers?",
    "options": [
      "Definitely will",
      "It might",
      "Not sure",
      "Probably not",
      "Definitely not"
    ],
    "correctAnswer": ""
  },
  {
    "id": 17,
    "question": "Do you think brand awareness is an important factor in choosing a mattress?",
    "options": [
      "Very important",
      "It's more important",
      "General",
      "Not very important",
      "Not important at all"
    ],
    "correctAnswer": ""
  },
  {
    "id": 18,
    "question": "Have you heard of the following mattress brands? (Multiple options available)",
    "options": [
      "Simmons",
      "Silk Ripple",
      "Tapper",
      "Kim Ke'er",
      "Moose",
      "Never heard of them"
    ],
    "correctAnswer": ""
  },
  {
    "id": 19,
    "question": "Do you think the air permeability of the mattress is very important?",
    "options": [
      "Very important",
      "It's more important",
      "General",
      "Not very important",
      "Not important at all"
    ],
    "correctAnswer": ""
  },
  {
    "id": 20,
    "question": "Do you think the anti-bacterial and anti-mite function of the mattress is necessary?",
    "options": [
      "Very necessary",
      "It is necessary",
      "It doesn't matter",
      "Not necessary",
      "Absolutely not necessary"
    ],
    "correctAnswer": ""
  },
  {
    "id": 21,
    "question": "Will you choose to buy a mattress because of its environmental certification?",
    "options": [
      "Definitely will",
      "It might",
      "Not sure",
      "Probably not",
      "Definitely not"
    ],
    "correctAnswer": ""
  },
  {
    "id": 22,
    "question": "Do you think the edge support of the mattress is important?",
    "options": [
      "Very important",
      "It's more important",
      "General",
      "Not very important",
      "Not important at all"
    ],
    "correctAnswer": ""
  },
  {
    "id": 23,
    "question": "Do you think the mute effect of the mattress is important?",
    "options": [
      "Very important",
      "It's more important",
      "General",
      "Not very important",
      "Not important at all"
    ],
    "correctAnswer": ""
  },
  {
    "id": 24,
    "question": "Will you choose a foldable mattress?",
    "options": [
      "Definitely will",
      "It might",
      "Not sure",
      "Probably not",
      "Definitely not"
    ],
    "correctAnswer": ""
  },
  {
    "id": 25,
    "question": "Will you choose a mattress with heating function?",
    "options": [
      "Definitely will",
      "It might",
      "Not sure",
      "Probably not",
      "Definitely not"
    ],
    "correctAnswer": ""
  },
  {
    "id": 26,
    "question": "Will you choose a mattress with massage function?",
    "options": [
      "Definitely will",
      "It might",
      "Not sure",
      "Probably not",
      "Definitely not"
    ],
    "correctAnswer": ""
  },
  {
    "id": 27,
    "question": "Will you choose a mattress with a zone design (such as different support for head, waist and legs)?",
    "options": [
      "Definitely will",
      "It might",
      "Not sure",
      "Probably not",
      "Definitely not"
    ],
    "correctAnswer": ""
  },
  {
    "id": 28,
    "question": "Will you choose a mattress that can adjust the firmness?",
    "options": [
      "Definitely will",
      "It might",
      "Not sure",
      "Probably not",
      "Definitely not"
    ],
    "correctAnswer": ""
  },
  {
    "id": 29,
    "question": "Will you choose a mattress with moisture resistance?",
    "options": [
      "Definitely will",
      "It might",
      "Not sure",
      "Probably not",
      "Definitely not"
    ],
    "correctAnswer": ""
  },
  {
    "id": 30,
    "question": "Will you choose a mattress with fire protection?",
    "options": [
      "Definitely will",
      "It might",
      "Not sure",
      "Probably not",
      "Definitely not"
    ],
    "correctAnswer": ""
  },
  {
    "id": 31,
    "question": "Will you choose a mattress with intelligent sleep monitoring function?",
    "options": [
      "Definitely will",
      "It might",
      "Not sure",
      "Probably not",
      "Definitely not"
    ],
    "correctAnswer": ""
  },
  {
    "id": 32,
    "question": "Will you choose a mattress with automatic temperature adjustment?",
    "options": [
      "Definitely will",
      "It might",
      "Not sure",
      "Probably not",
      "Definitely not"
    ],
    "correctAnswer": ""
  },
  {
    "id": 33,
    "question": "Will you choose a mattress with negative ion release function?",
    "options": [
      "Definitely will",
      "It might",
      "Not sure",
      "Probably not",
      "Definitely not"
    ],
    "correctAnswer": ""
  },
  {
    "id": 34,
    "question": "Will you choose a mattress with far-infrared function?",
    "options": [
      "Definitely will",
      "It might",
      "Not sure",
      "Probably not",
      "Definitely not"
    ],
    "correctAnswer": ""
  },
  {
    "id": 35,
    "question": "Will you choose a mattress with magnetic therapy function?",
    "options": [
      "Definitely will",
      "It might",
      "Not sure",
      "Probably not",
      "Definitely not"
    ],
    "correctAnswer": ""
  },
  {
    "id": 36,
    "question": "Will you choose a mattress with spa functions?",
    "options": [
      "Definitely will",
      "It might",
      "Not sure",
      "Probably not",
      "Definitely not"
    ],
    "correctAnswer": ""
  },
  {
    "id": 37,
    "question": "Will you choose a mattress with aromatherapy function?",
    "options": [
      "Definitely will",
      "It might",
      "Not sure",
      "Probably not",
      "Definitely not"
    ],
    "correctAnswer": ""
  },
  {
    "id": 38,
    "question": "Will you choose a mattress with the function of playing sleep music?",
    "options": [
      "Definitely will",
      "It might",
      "Not sure",
      "Probably not",
      "Definitely not"
    ],
    "correctAnswer": ""
  },
  {
    "id": 39,
    "question": "Will you choose a mattress with phototherapy function?",
    "options": [
      "Definitely will",
      "It might",
      "Not sure",
      "Probably not",
      "Definitely not"
    ],
    "correctAnswer": ""
  },
  {
    "id": 40,
    "question": "Will you choose a mattress with yoga function?",
    "options": [
      "Definitely will",
      "It might",
      "Not sure",
      "Probably not",
      "Definitely not"
    ],
    "correctAnswer": ""
  },
  {
    "id": 41,
    "question": "Will you choose a mattress with child protection?",
    "options": [
      "Definitely will",
      "It might",
      "Not sure",
      "Probably not",
      "Definitely not"
    ],
    "correctAnswer": ""
  },
  {
    "id": 42,
    "question": "Will you choose a mattress with special functions for pregnant women?",
    "options": [
      "Definitely will",
      "It might",
      "Not sure",
      "Probably not",
      "Definitely not"
    ],
    "correctAnswer": ""
  },
  {
    "id": 43,
    "question": "Will you choose a mattress with elderly care function?",
    "options": [
      "Definitely will",
      "It might",
      "Not sure",
      "Probably not",
      "Definitely not"
    ],
    "correctAnswer": ""
  },
  {
    "id": 44,
    "question": "Will you choose a mattress with athlete recovery function?",
    "options": [
      "Definitely will",
      "It might",
      "Not sure",
      "Probably not",
      "Definitely not"
    ],
    "correctAnswer": ""
  },
  {
    "id": 45,
    "question": "Will you choose a mattress with pet-specific features?",
    "options": [
      "Definitely will",
      "It might",
      "Not sure",
      "Probably not",
      "Definitely not"
    ],
    "correctAnswer": ""
  },
  {
    "id": 46,
    "question": "Will you choose a mattress made of space memory cotton?",
    "options": [
      "Definitely will",
      "It might",
      "Not sure",
      "Probably not",
      "Definitely not"
    ],
    "correctAnswer": ""
  },
  {
    "id": 47,
    "question": "Will you choose a mattress made of bamboo charcoal fiber?",
    "options": [
      "Definitely will",
      "It might",
      "Not sure",
      "Probably not",
      "Definitely not"
    ],
    "correctAnswer": ""
  },
  {
    "id": 48,
    "question": "Will you choose a mattress made of coconut?",
    "options": [
      "Definitely will",
      "It might",
      "Not sure",
      "Probably not",
      "Definitely not"
    ],
    "correctAnswer": ""
  },
  {
    "id": 49,
    "question": "Will you choose a mattress made of wool?",
    "options": [
      "Definitely will",
      "It might",
      "Not sure",
      "Probably not",
      "Definitely not"
    ],
    "correctAnswer": ""
  },
  {
    "id": 50,
    "question": "Will you choose a mattress with down material?",
    "options": [
      "Definitely will",
      "It might",
      "Not sure",
      "Probably not",
      "Definitely not"
    ],
    "correctAnswer": ""
  },
  {
    "id": 51,
    "question": "Will you choose a mattress with gel material?",
    "options": [
      "Definitely will",
      "It might",
      "Not sure",
      "Probably not",
      "Definitely not"
    ],
    "correctAnswer": ""
  },
  {
    "id": 52,
    "question": "Will you choose a mattress made of sponge?",
    "options": [
      "Definitely will",
      "It might",
      "Not sure",
      "Probably not",
      "Definitely not"
    ],
    "correctAnswer": ""
  },
  {
    "id": 53,
    "question": "Will you choose a mattress made of linen?",
    "options": [
      "Definitely will",
      "It might",
      "Not sure",
      "Probably not",
      "Definitely not"
    ],
    "correctAnswer": ""
  },
  {
    "id": 54,
    "question": "Would you choose a mattress made of silk?",
    "options": [
      "Definitely will",
      "It might",
      "Not sure",
      "Probably not",
      "Definitely not"
    ],
    "correctAnswer": ""
  },
  {
    "id": 55,
    "question": "Will you choose a mattress made of pure cotton?",
    "options": [
      "Definitely will",
      "It might",
      "Not sure",
      " Probably not",
      "Definitely not"
    ],
    "correctAnswer": ""
  },
  {
    "id": 56,
    "question": "Will you choose a mattress made of chemical fiber?",
    "options": [
      "Definitely will",
      "It might",
      "Not sure",
      " Probably not",
      "Definitely not"
    ],
    "correctAnswer": ""
  },
  {
    "id": 57,
    "question": "Will you choose a mattress with 3D material?",
    "options": [
      "Definitely will",
      "It might",
      "Not sure",
      " Probably not",
      "Definitely not"
    ],
    "correctAnswer": ""
  },
  {
    "id": 58,
    "question": "Will you choose a mattress with nano-materials?",
    "options": [
      "Definitely will",
      "It might",
      "Not sure",
      " Probably not",
      "Definitely not"
    ],
    "correctAnswer": ""
  },
  {
    "id": 59,
    "question": "Will you choose a mattress made of carbon fiber?",
    "options": [
      "Definitely will",
      "It might",
      "Not sure",
      " Probably not",
      "Definitely not"
    ],
    "correctAnswer": ""
  },
  {
    "id": 60,
    "question": "Will you choose a mattress made of fiberglass?",
    "options": [
      "Definitely will",
      "It might",
      "Not sure",
      " Probably not",
      "Definitely not"
    ],
    "correctAnswer": ""
  },
  {
    "id": 61,
    "question": "Will you choose a mattress with latex + spring combination?",
    "options": [
      "Definitely will",
      "It might",
      "Not sure",
      " Probably not",
      "Definitely not"
    ],
    "correctAnswer": ""
  },
  {
    "id": 62,
    "question": "Will you choose a mattress with memory cotton + spring combination?",
    "options": [
      "Definitely will",
      "It might",
      "Not sure",
      " Probably not",
      "Definitely not"
    ],
    "correctAnswer": ""
  },
  {
    "id": 63,
    "question": "Will you choose a mattress with a combination of palm cushion and spring?",
    "options": [
      "Definitely will",
      "It might",
      "Not sure",
      " Probably not",
      "Definitely not"
    ],
    "correctAnswer": ""
  },
  {
    "id": 64,
    "question": "Will you choose a mattress with latex + memory cotton combination?",
    "options": [
      "Definitely will",
      "It might",
      "Not sure",
      " Probably not",
      "Definitely not"
    ],
    "correctAnswer": ""
  },
  {
    "id": 65,
    "question": "Will you choose a mattress with latex + palm cushion combination?",
    "options": [
      "Definitely will",
      "It might",
      "Not sure",
      " Probably not",
      "Definitely not"
    ],
    "correctAnswer": ""
  },
  {
    "id": 66,
    "question": "Will you choose a mattress with a combination of memory cotton and palm cushion?",
    "options": [
      "Definitely will",
      "It might",
      "Not sure",
      " Probably not",
      "Definitely not"
    ],
    "correctAnswer": ""
  },
  {
    "id": 67,
    "question": "Will you choose a mattress with spring + mat + latex combination?",
    "options": [
      "Definitely will",
      "It might",
      "Not sure",
      " Probably not",
      "Definitely not"
    ],
    "correctAnswer": ""
  },
  {
    "id": 68,
    "question": "Will you choose a mattress with spring + memory cotton + latex combination?",
    "options": [
      "Definitely will",
      "It might",
      "Not sure",
      " Probably not",
      "Definitely not"
    ],
    "correctAnswer": ""
  },
  {
    "id": 69,
    "question": "Will you choose a mattress with spring + palm mat + memory foam combination?",
    "options": [
      "Definitely will",
      "It might",
      "Not sure",
      " Probably not",
      "Definitely not"
    ],
    "correctAnswer": ""
  },
  {
    "id": 70,
    "question": "Will you choose a mattress with latex + palm mat + memory cotton + spring combination?",
    "options": [
      "Definitely will",
      "It might",
      "Not sure",
      " Probably not",
      "Definitely not"
    ],
    "correctAnswer": ""
  },
  {
    "id": 71,
    "question": "Will you choose a mattress with separate bagged springs?",
    "options": [
      "Definitely will",
      "It might",
      "Not sure",
      " Probably not",
      "Definitely not"
    ],
    "correctAnswer": ""
  },
  {
    "id": 72,
    "question": "Will you choose a mattress with full mesh springs?",
    "options": [
      "Definitely will",
      "It might",
      "Not sure",
      " Probably not",
      "Definitely not"
    ],
    "correctAnswer": ""
  },
  {
    "id": 73,
    "question": "Will you choose a mattress with double spring?",
    "options": [
      "Definitely will",
      "It might",
      "Not sure",
      " Probably not",
      "Definitely not"
    ],
    "correctAnswer": ""
  },
  {
    "id": 74,
    "question": "Will you choose a mattress with three zone springs?",
    "options": [
      "Definitely will",
      "It might",
      "Not sure",
      " Probably not",
      "Definitely not"
    ],
    "correctAnswer": ""
  },
  {
    "id": 75,
    "question": "Will you choose a mattress with five zone springs?",
    "options": [
      "Definitely will",
      "It might",
      "Not sure",
      " Probably not",
      "Definitely not"
    ],
    "correctAnswer": ""
  },
  {
    "id": 76,
    "question": "Will you choose a mattress with seven zone springs?",
    "options": [
      "Definitely will",
      "It might",
      "Not sure",
      " Probably not",
      "Definitely not"
    ],
    "correctAnswer": ""
  },
  {
    "id": 77,
    "question": "Will you choose a mattress with a nine-zone spring?",
    "options": [
      "Definitely will",
      "It might",
      "Not sure",
      " Probably not",
      "Definitely not"
    ],
    "correctAnswer": ""
  },
  {
    "id": 78,
    "question": "Will you choose a mattress with 10-zone springs?",
    "options": [
      "Definitely will",
      "It might",
      "Not sure",
      " Probably not",
      "Definitely not"
    ],
    "correctAnswer": ""
  },
  {
    "id": 79,
    "question": "Would you choose a mattress with round springs?",
    "options": [
      "Definitely will",
      "It might",
      "Not sure",
      " Probably not",
      "Definitely not"
    ],
    "correctAnswer": ""
  },
  {
    "id": 80,
    "question": "Will you choose a mattress with an hourglass spring?",
    "options": [
      "Definitely will",
      "It might",
      "Not sure",
      " Probably not",
      "Definitely not"
    ],
    "correctAnswer": ""
  }
]